one2x_sdk/__init__.py
one2x_sdk/medeo/__init__.py
one2x_sdk/medeo/core_api/__init__.py
one2x_sdk/medeo/core_api/core_api_client.py
one2x_sdk/medeo/task/__init__.py
one2x_sdk/medeo/task/basic_task_polling_service.py
one2x_sdk/tools/__init__.py
one2x_sdk/tools/request_monitor.py
one2x_sdk/utils/__init__.py
one2x_sdk/utils/logger.py
tests/__init__.py
tests/medeo/__init__.py
tests/medeo/task/__init__.py
tests/medeo/task/test_basic_task_polling_service.py
one2x_sdk-0.0.31.dist-info/LICENSE
one2x_sdk-0.0.31.dist-info/METADATA
one2x_sdk-0.0.31.dist-info/WHEEL
one2x_sdk-0.0.31.dist-info/top_level.txt
one2x_sdk-0.0.31.dist-info/RECORD
